<?xml version="1.0" encoding="UTF-8" ?>
<!DOCTYPE mapper PUBLIC "-//mybatis.org//DTD Mapper 3.0//EN" "http://mybatis.org/dtd/mybatis-3-mapper.dtd" >
<mapper namespace="cn.douzy.remainder.dao.ContentMapper" >
  <resultMap id="BaseResultMap" type="cn.douzy.remainder.entity.Content" >
    <!--
      WARNING - @mbggenerated
      This element is automatically generated by MyBatis Generator, do not modify.
      This element was generated on Wed Jul 12 14:40:34 CST 2017.
    -->
    <id column="id" property="id" jdbcType="INTEGER" />
    <result column="create_time" property="createTime" jdbcType="TIMESTAMP" />
  </resultMap>
  <resultMap id="ResultMapWithBLOBs" type="cn.douzy.remainder.entity.Content" extends="BaseResultMap" >
    <!--
      WARNING - @mbggenerated
      This element is automatically generated by MyBatis Generator, do not modify.
      This element was generated on Wed Jul 12 14:40:34 CST 2017.
    -->
    <result column="con" property="con" jdbcType="LONGVARCHAR" />
  </resultMap>
  <sql id="Base_Column_List" >
    <!--
      WARNING - @mbggenerated
      This element is automatically generated by MyBatis Generator, do not modify.
      This element was generated on Wed Jul 12 14:40:34 CST 2017.
    -->
    id, create_time
  </sql>
  <sql id="Blob_Column_List" >
    <!--
      WARNING - @mbggenerated
      This element is automatically generated by MyBatis Generator, do not modify.
      This element was generated on Wed Jul 12 14:40:34 CST 2017.
    -->
    con
  </sql>
  <select id="selectByPrimaryKey" resultMap="ResultMapWithBLOBs" parameterType="java.lang.Integer" >
    <!--
      WARNING - @mbggenerated
      This element is automatically generated by MyBatis Generator, do not modify.
      This element was generated on Wed Jul 12 14:40:34 CST 2017.
    -->
    select 
    <include refid="Base_Column_List" />
    ,
    <include refid="Blob_Column_List" />
    from content
    where id = #{id,jdbcType=INTEGER}
  </select>
  <delete id="deleteByPrimaryKey" parameterType="java.lang.Integer" >
    <!--
      WARNING - @mbggenerated
      This element is automatically generated by MyBatis Generator, do not modify.
      This element was generated on Wed Jul 12 14:40:34 CST 2017.
    -->
    delete from content
    where id = #{id,jdbcType=INTEGER}
  </delete>
  <insert id="insert" parameterType="cn.douzy.remainder.entity.Content" >
    <!--
      WARNING - @mbggenerated
      This element is automatically generated by MyBatis Generator, do not modify.
      This element was generated on Wed Jul 12 14:40:34 CST 2017.
    -->
    insert into content (id, create_time, con
      )
    values (#{id,jdbcType=INTEGER}, #{createTime,jdbcType=TIMESTAMP}, #{con,jdbcType=LONGVARCHAR}
      )
  </insert>
  <insert id="insertSelective" parameterType="cn.douzy.remainder.entity.Content" >
    <!--
      WARNING - @mbggenerated
      This element is automatically generated by MyBatis Generator, do not modify.
      This element was generated on Wed Jul 12 14:40:34 CST 2017.
    -->
    insert into content
    <trim prefix="(" suffix=")" suffixOverrides="," >
      <if test="id != null" >
        id,
      </if>
      <if test="createTime != null" >
        create_time,
      </if>
      <if test="con != null" >
        con,
      </if>
    </trim>
    <trim prefix="values (" suffix=")" suffixOverrides="," >
      <if test="id != null" >
        #{id,jdbcType=INTEGER},
      </if>
      <if test="createTime != null" >
        #{createTime,jdbcType=TIMESTAMP},
      </if>
      <if test="con != null" >
        #{con,jdbcType=LONGVARCHAR},
      </if>
    </trim>
  </insert>
  <update id="updateByPrimaryKeySelective" parameterType="cn.douzy.remainder.entity.Content" >
    <!--
      WARNING - @mbggenerated
      This element is automatically generated by MyBatis Generator, do not modify.
      This element was generated on Wed Jul 12 14:40:34 CST 2017.
    -->
    update content
    <set >
      <if test="createTime != null" >
        create_time = #{createTime,jdbcType=TIMESTAMP},
      </if>
      <if test="con != null" >
        con = #{con,jdbcType=LONGVARCHAR},
      </if>
    </set>
    where id = #{id,jdbcType=INTEGER}
  </update>
  <update id="updateByPrimaryKeyWithBLOBs" parameterType="cn.douzy.remainder.entity.Content" >
    <!--
      WARNING - @mbggenerated
      This element is automatically generated by MyBatis Generator, do not modify.
      This element was generated on Wed Jul 12 14:40:34 CST 2017.
    -->
    update content
    set create_time = #{createTime,jdbcType=TIMESTAMP},
      con = #{con,jdbcType=LONGVARCHAR}
    where id = #{id,jdbcType=INTEGER}
  </update>
  <update id="updateByPrimaryKey" parameterType="cn.douzy.remainder.entity.Content" >
    <!--
      WARNING - @mbggenerated
      This element is automatically generated by MyBatis Generator, do not modify.
      This element was generated on Wed Jul 12 14:40:34 CST 2017.
    -->
    update content
    set create_time = #{createTime,jdbcType=TIMESTAMP}
    where id = #{id,jdbcType=INTEGER}
  </update>
  <select id="selectModel" resultMap="BaseResultMap" parameterType="java.util.Map" >
    select 
    <include refid="Base_Column_List" />
     from 
     remainder.content
    <where >
      <if test="id != null" >
         and id= #{id,jdbcType=INTEGER}
      </if>
      <if test="createTime != null" >
         and create_time= #{createTime,jdbcType=TIMESTAMP}
      </if>
      <if test="con != null" >
         and con= #{con,jdbcType=LONGVARCHAR}
      </if>
    </where>
    <if test="order != null" >
      <![CDATA[  order by  ${order} ]]>
    </if>
  </select>
  <select id="selectList" resultMap="BaseResultMap" parameterType="java.util.Map" >
    select 
    <include refid="Base_Column_List" />
     from 
     remainder.content
    <where >
      <if test="id != null" >
         and id= #{id,jdbcType=INTEGER}
      </if>
      <if test="createTime != null" >
         and create_time= #{createTime,jdbcType=TIMESTAMP}
      </if>
      <if test="con != null" >
         and con= #{con,jdbcType=LONGVARCHAR}
      </if>
    </where>
    <if test="order != null" >
      <![CDATA[  order by  ${order} ]]>
    </if>
  </select>
  <select id="selectPageList" resultMap="BaseResultMap" parameterType="java.util.Map" >
    select 
    <include refid="Base_Column_List" />
     from 
     remainder.content
    <where >
      <if test="id != null" >
         and id= #{id,jdbcType=INTEGER}
      </if>
      <if test="createTime != null" >
         and create_time= #{createTime,jdbcType=TIMESTAMP}
      </if>
      <if test="con != null" >
         and con= #{con,jdbcType=LONGVARCHAR}
      </if>
    </where>
    <if test="order != null" >
      <![CDATA[  order by  ${order} ]]>
    </if>
    <if test="page != null" >
      <![CDATA[  limit #{page.begin}, #{page.end} ]]>
    </if>
  </select>
  <select id="selectCount" resultType="int" parameterType="java.util.Map" >
     select
     count(1)
     from 
     remainder.content
    <where >
      <if test="id != null" >
         and id= #{id,jdbcType=INTEGER}
      </if>
      <if test="createTime != null" >
         and create_time= #{createTime,jdbcType=TIMESTAMP}
      </if>
      <if test="con != null" >
         and con= #{con,jdbcType=LONGVARCHAR}
      </if>
    </where>
  </select>
</mapper>